spanet/__init__.py
spanet/evaluation.py
spanet/export.py
spanet/options.py
spanet/predict.py
spanet/test.py
spanet/train.py
spanet/dataset/__init__.py
spanet/dataset/evaluator.py
spanet/dataset/event_info.py
spanet/dataset/jet_reconstruction_dataset.py
spanet/dataset/types.py
spanet/dataset/inputs/BaseInput.py
spanet/dataset/inputs/GlobalInput.py
spanet/dataset/inputs/RelativeInput.py
spanet/dataset/inputs/SequentialInput.py
spanet/dataset/inputs/__init__.py
spanet/dataset/regressions/__init__.py
spanet/dataset/regressions/base_regression.py
spanet/dataset/regressions/gaussian_regression.py
spanet/dataset/regressions/laplacian_regression.py
spanet/dataset/regressions/log_gaussian_regression.py
spanet/network/__init__.py
spanet/network/learning_rate_schedules.py
spanet/network/prediction_selection.py
spanet/network/prediction_selection_old.py
spanet/network/jet_reconstruction/__init__.py
spanet/network/jet_reconstruction/jet_reconstruction_base.py
spanet/network/jet_reconstruction/jet_reconstruction_network.py
spanet/network/jet_reconstruction/jet_reconstruction_optimization.py
spanet/network/jet_reconstruction/jet_reconstruction_training.py
spanet/network/jet_reconstruction/jet_reconstruction_validation.py
spanet/network/jet_reconstruction/sherpa_network.py
spanet/network/layers/__init__.py
spanet/network/layers/branch_decoder.py
spanet/network/layers/classification_decoder.py
spanet/network/layers/embedding_stack.py
spanet/network/layers/linear_stack.py
spanet/network/layers/regression_decoder.py
spanet/network/layers/stacked_encoder.py
spanet/network/layers/vector_encoder.py
spanet/network/layers/branch_linear/__init__.py
spanet/network/layers/branch_linear/branch_linear.py
spanet/network/layers/branch_linear/multioutput_branch_linear.py
spanet/network/layers/branch_linear/normalized_branch_linear.py
spanet/network/layers/embedding/__init__.py
spanet/network/layers/embedding/combined_vector_embedding.py
spanet/network/layers/embedding/global_vector_embedding.py
spanet-2.1.1.dist-info/LICENSE
spanet-2.1.1.dist-info/METADATA
spanet-2.1.1.dist-info/WHEEL
spanet-2.1.1.dist-info/top_level.txt
spanet-2.1.1.dist-info/RECORD
